pypanter/__init__.py
pypanter/main.py
pypanter-0.0.1.dist-info/LICENSE
pypanter-0.0.1.dist-info/METADATA
pypanter-0.0.1.dist-info/WHEEL
pypanter-0.0.1.dist-info/top_level.txt
pypanter-0.0.1.dist-info/RECORD
