Metadata-Version: 2.1
Name: pypanter
Version: 0.0.1
Summary: UNKNOWN
Home-page: https://github.com/Kekkodf/pypanter
Author: Francesco L. De Faveri
Author-email: francescoluigi.defaveri@phd.unipd.it
License: UNKNOWN
Project-URL: Bug Reports, https://github.com/Kekkodf/pypanter/issues
Project-URL: Source, https://github.com/Kekkodf/pypanter
Keywords: Differential Privacy,NLP,Obfuscation,Anonymization
Platform: UNKNOWN
License-File: LICENSE
Requires-Dist: numpy
Requires-Dist: pandas
Requires-Dist: scipy
